{
  "id": "2895448",
  "name": "test",
  "font_family": "iconfont",
  "css_prefix_text": "icon-",
  "description": "",
  "glyphs": [
    {
      "icon_id": "1302",
      "name": "加",
      "font_class": "jia",
      "unicode": "e644",
      "unicode_decimal": 58948
    },
    {
      "icon_id": "162780",
      "name": "加",
      "font_class": "jia1",
      "unicode": "e645",
      "unicode_decimal": 58949
    },
    {
      "icon_id": "666893",
      "name": "系统返回",
      "font_class": "xitongfanhui",
      "unicode": "e698",
      "unicode_decimal": 59032
    },
    {
      "icon_id": "687392",
      "name": "返回",
      "font_class": "fanhui",
      "unicode": "e6ff",
      "unicode_decimal": 59135
    },
    {
      "icon_id": "4766966",
      "name": "man",
      "font_class": "man",
      "unicode": "e7e2",
      "unicode_decimal": 59362
    },
    {
      "icon_id": "7736025",
      "name": "exchange",
      "font_class": "exchange",
      "unicode": "e8e4",
      "unicode_decimal": 59620
    },
    {
      "icon_id": "8952781",
      "name": "exchange",
      "font_class": "exchange1",
      "unicode": "e801",
      "unicode_decimal": 59393
    },
    {
      "icon_id": "14629166",
      "name": "empty-status",
      "font_class": "empty-status",
      "unicode": "e646",
      "unicode_decimal": 58950
    },
    {
      "icon_id": "16036026",
      "name": "folder-zip-fill",
      "font_class": "folder-zip-fill",
      "unicode": "e75c",
      "unicode_decimal": 59228
    },
    {
      "icon_id": "18592406",
      "name": "exchange",
      "font_class": "exchange2",
      "unicode": "e682",
      "unicode_decimal": 59010
    },
    {
      "icon_id": "4766693",
      "name": "unlike",
      "font_class": "unlike",
      "unicode": "e7c8",
      "unicode_decimal": 59336
    },
    {
      "icon_id": "11982730",
      "name": "Dislike, unlike, thumb down",
      "font_class": "Dislikeunlikethumbdown",
      "unicode": "e9d7",
      "unicode_decimal": 59863
    },
    {
      "icon_id": "309253",
      "name": "backtop",
      "font_class": "backtop",
      "unicode": "e6c6",
      "unicode_decimal": 59078
    },
    {
      "icon_id": "1112553",
      "name": "message",
      "font_class": "message",
      "unicode": "e63f",
      "unicode_decimal": 58943
    },
    {
      "icon_id": "6598354",
      "name": "woman",
      "font_class": "woman",
      "unicode": "e8f2",
      "unicode_decimal": 59634
    },
    {
      "icon_id": "7674867",
      "name": "收起",
      "font_class": "daohangshouqi-",
      "unicode": "e712",
      "unicode_decimal": 59154
    },
    {
      "icon_id": "9218217",
      "name": "message",
      "font_class": "message1",
      "unicode": "e640",
      "unicode_decimal": 58944
    },
    {
      "icon_id": "15838545",
      "name": "top",
      "font_class": "top",
      "unicode": "e681",
      "unicode_decimal": 59009
    },
    {
      "icon_id": "27128168",
      "name": "128-展开/收起",
      "font_class": "shouqi2-01",
      "unicode": "e67a",
      "unicode_decimal": 59002
    },
    {
      "icon_id": "27128183",
      "name": "129-收起/展开",
      "font_class": "shouqi-01-copy",
      "unicode": "e67b",
      "unicode_decimal": 59003
    },
    {
      "icon_id": "27386196",
      "name": "zhuce",
      "font_class": "zhuce",
      "unicode": "e642",
      "unicode_decimal": 58946
    },
    {
      "icon_id": "32880696",
      "name": "注册",
      "font_class": "zhuce1",
      "unicode": "e65e",
      "unicode_decimal": 58974
    },
    {
      "icon_id": "135132",
      "name": "积分",
      "font_class": "jifen",
      "unicode": "e631",
      "unicode_decimal": 58929
    },
    {
      "icon_id": "200967",
      "name": "3.1点赞",
      "font_class": "31dianzan",
      "unicode": "e633",
      "unicode_decimal": 58931
    },
    {
      "icon_id": "265327",
      "name": " attachment",
      "font_class": "attachment",
      "unicode": "e6a9",
      "unicode_decimal": 59049
    },
    {
      "icon_id": "321993",
      "name": "integral",
      "font_class": "jifen1",
      "unicode": "e70c",
      "unicode_decimal": 59148
    },
    {
      "icon_id": "1160510",
      "name": "image",
      "font_class": "image",
      "unicode": "e70e",
      "unicode_decimal": 59150
    },
    {
      "icon_id": "1270661",
      "name": "发帖_icon",
      "font_class": "fatie_icon",
      "unicode": "e669",
      "unicode_decimal": 58985
    },
    {
      "icon_id": "1311634",
      "name": "账户",
      "font_class": "zhanghu",
      "unicode": "e634",
      "unicode_decimal": 58932
    },
    {
      "icon_id": "3427805",
      "name": "附件",
      "font_class": "icon-",
      "unicode": "e635",
      "unicode_decimal": 58933
    },
    {
      "icon_id": "4766917",
      "name": "image",
      "font_class": "image1",
      "unicode": "e7de",
      "unicode_decimal": 59358
    },
    {
      "icon_id": "5635025",
      "name": "image",
      "font_class": "image2",
      "unicode": "f2b6",
      "unicode_decimal": 62134
    },
    {
      "icon_id": "6151070",
      "name": "edit",
      "font_class": "edit",
      "unicode": "e7a0",
      "unicode_decimal": 59296
    },
    {
      "icon_id": "8455373",
      "name": "验证码",
      "font_class": "yanzhengma",
      "unicode": "e636",
      "unicode_decimal": 58934
    },
    {
      "icon_id": "12903223",
      "name": "email",
      "font_class": "email",
      "unicode": "e63c",
      "unicode_decimal": 58940
    },
    {
      "icon_id": "15162661",
      "name": "dianzan",
      "font_class": "dianzan",
      "unicode": "e63d",
      "unicode_decimal": 58941
    },
    {
      "icon_id": "16042634",
      "name": "验证码",
      "font_class": "yanzhengma1",
      "unicode": "e64d",
      "unicode_decimal": 58957
    },
    {
      "icon_id": "16618154",
      "name": "edit",
      "font_class": "edit1",
      "unicode": "e6aa",
      "unicode_decimal": 59050
    },
    {
      "icon_id": "21096621",
      "name": "email",
      "font_class": "email1",
      "unicode": "ecb1",
      "unicode_decimal": 60593
    },
    {
      "icon_id": "34453208",
      "name": "email",
      "font_class": "email2",
      "unicode": "e856",
      "unicode_decimal": 59478
    },
    {
      "icon_id": "18167099",
      "name": "警察半身,公安",
      "font_class": "policeman-full",
      "unicode": "e8f1",
      "unicode_decimal": 59633
    },
    {
      "icon_id": "18799722",
      "name": "派出所",
      "font_class": "paichusuo",
      "unicode": "e630",
      "unicode_decimal": 58928
    },
    {
      "icon_id": "1360",
      "name": "新浪微博",
      "font_class": "xinlangweibo",
      "unicode": "e622",
      "unicode_decimal": 58914
    },
    {
      "icon_id": "77156",
      "name": "微信",
      "font_class": "weixin2",
      "unicode": "e623",
      "unicode_decimal": 58915
    },
    {
      "icon_id": "201555",
      "name": "表情",
      "font_class": "biaoqing",
      "unicode": "e625",
      "unicode_decimal": 58917
    },
    {
      "icon_id": "1471079",
      "name": "表情",
      "font_class": "biaoqing-xue",
      "unicode": "e632",
      "unicode_decimal": 58930
    },
    {
      "icon_id": "1582883",
      "name": "讨论",
      "font_class": "taolun",
      "unicode": "e643",
      "unicode_decimal": 58947
    },
    {
      "icon_id": "1719343",
      "name": "随机",
      "font_class": "suiji",
      "unicode": "e7b8",
      "unicode_decimal": 59320
    },
    {
      "icon_id": "3865279",
      "name": "讨论",
      "font_class": "taolun1",
      "unicode": "e627",
      "unicode_decimal": 58919
    },
    {
      "icon_id": "5699519",
      "name": "微博",
      "font_class": "weibo",
      "unicode": "e62f",
      "unicode_decimal": 58927
    },
    {
      "icon_id": "9186712",
      "name": "微博",
      "font_class": "weibo1",
      "unicode": "e666",
      "unicode_decimal": 58982
    },
    {
      "icon_id": "11776582",
      "name": "微博",
      "font_class": "weibo2",
      "unicode": "e628",
      "unicode_decimal": 58920
    },
    {
      "icon_id": "18167087",
      "name": "警察,公安",
      "font_class": "police",
      "unicode": "e8f0",
      "unicode_decimal": 59632
    },
    {
      "icon_id": "31154",
      "name": "设置",
      "font_class": "shezhi",
      "unicode": "e629",
      "unicode_decimal": 58921
    },
    {
      "icon_id": "108776",
      "name": "删除",
      "font_class": "shanchu",
      "unicode": "e61e",
      "unicode_decimal": 58910
    },
    {
      "icon_id": "1727421",
      "name": "205设置-线性",
      "font_class": "shezhi-xianxing",
      "unicode": "e8b7",
      "unicode_decimal": 59575
    },
    {
      "icon_id": "3283216",
      "name": "角色删除",
      "font_class": "remove-role",
      "unicode": "e620",
      "unicode_decimal": 58912
    },
    {
      "icon_id": "3283486",
      "name": "角色设置",
      "font_class": "setting-role",
      "unicode": "e621",
      "unicode_decimal": 58913
    },
    {
      "icon_id": "3538379",
      "name": "删除",
      "font_class": "shanchu1",
      "unicode": "e718",
      "unicode_decimal": 59160
    },
    {
      "icon_id": "5387546",
      "name": "全局设置",
      "font_class": "quanjushezhi",
      "unicode": "eafb",
      "unicode_decimal": 60155
    },
    {
      "icon_id": "11372693",
      "name": "删除",
      "font_class": "shanchu2",
      "unicode": "e8b6",
      "unicode_decimal": 59574
    },
    {
      "icon_id": "1330569",
      "name": "微信",
      "font_class": "weixin",
      "unicode": "e73b",
      "unicode_decimal": 59195
    },
    {
      "icon_id": "4546550",
      "name": "csdn",
      "font_class": "csdn",
      "unicode": "e638",
      "unicode_decimal": 58936
    },
    {
      "icon_id": "4937000",
      "name": "github-fill",
      "font_class": "github-fill",
      "unicode": "e885",
      "unicode_decimal": 59525
    },
    {
      "icon_id": "5023514",
      "name": "做题",
      "font_class": "zuoti",
      "unicode": "e62a",
      "unicode_decimal": 58922
    },
    {
      "icon_id": "8289051",
      "name": "QQ",
      "font_class": "QQ",
      "unicode": "e876",
      "unicode_decimal": 59510
    },
    {
      "icon_id": "13253771",
      "name": "github",
      "font_class": "github",
      "unicode": "e615",
      "unicode_decimal": 58901
    },
    {
      "icon_id": "15933094",
      "name": "微信",
      "font_class": "weixin1",
      "unicode": "e617",
      "unicode_decimal": 58903
    },
    {
      "icon_id": "16543261",
      "name": "加题面板_题目",
      "font_class": "jiatimianban_timu",
      "unicode": "e656",
      "unicode_decimal": 58966
    },
    {
      "icon_id": "22320180",
      "name": "题目-04",
      "font_class": "timu-04",
      "unicode": "e61a",
      "unicode_decimal": 58906
    },
    {
      "icon_id": "23248273",
      "name": "做题",
      "font_class": "kaoshi",
      "unicode": "e61c",
      "unicode_decimal": 58908
    },
    {
      "icon_id": "845828",
      "name": "眼睛",
      "font_class": "yanjing1",
      "unicode": "e668",
      "unicode_decimal": 58984
    },
    {
      "icon_id": "1356161",
      "name": "眼睛-闭",
      "font_class": "yanjing-bi",
      "unicode": "e61d",
      "unicode_decimal": 58909
    },
    {
      "icon_id": "7310556",
      "name": "眼睛",
      "font_class": "yanjing2",
      "unicode": "e614",
      "unicode_decimal": 58900
    },
    {
      "icon_id": "10715460",
      "name": "眼睛-闭眼",
      "font_class": "yanjing-biyan",
      "unicode": "e63b",
      "unicode_decimal": 58939
    },
    {
      "icon_id": "29570596",
      "name": "关闭眼睛",
      "font_class": "guanbiyanjing",
      "unicode": "e6af",
      "unicode_decimal": 59055
    },
    {
      "icon_id": "1260",
      "name": "好友",
      "font_class": "haoyou",
      "unicode": "e60a",
      "unicode_decimal": 58890
    },
    {
      "icon_id": "6685",
      "name": "进口商品",
      "font_class": "jinkoushangpin",
      "unicode": "e60b",
      "unicode_decimal": 58891
    },
    {
      "icon_id": "88780",
      "name": "全部订单",
      "font_class": "quanbudingdan",
      "unicode": "e60c",
      "unicode_decimal": 58892
    },
    {
      "icon_id": "201644",
      "name": "3.1 全部商品",
      "font_class": "31quanbushangpin",
      "unicode": "e60d",
      "unicode_decimal": 58893
    },
    {
      "icon_id": "356464",
      "name": "商品",
      "font_class": "shangpin",
      "unicode": "e624",
      "unicode_decimal": 58916
    },
    {
      "icon_id": "507674",
      "name": "权限分级",
      "font_class": "quanxianfenji",
      "unicode": "e758",
      "unicode_decimal": 59224
    },
    {
      "icon_id": "577335",
      "name": "订单",
      "font_class": "dingdan",
      "unicode": "e737",
      "unicode_decimal": 59191
    },
    {
      "icon_id": "1094290",
      "name": "商品中心供货合作保证金",
      "font_class": "zhi",
      "unicode": "e68b",
      "unicode_decimal": 59019
    },
    {
      "icon_id": "1727269",
      "name": "06商品",
      "font_class": "shangpin1",
      "unicode": "e888",
      "unicode_decimal": 59528
    },
    {
      "icon_id": "1915205",
      "name": "数据统计",
      "font_class": "icon-test",
      "unicode": "e60e",
      "unicode_decimal": 58894
    },
    {
      "icon_id": "2076282",
      "name": " 订单",
      "font_class": "dingdan1",
      "unicode": "e897",
      "unicode_decimal": 59543
    },
    {
      "icon_id": "2076283",
      "name": " 订单集合",
      "font_class": "dingdanjihe",
      "unicode": "e898",
      "unicode_decimal": 59544
    },
    {
      "icon_id": "6129157",
      "name": "116订单、订单明细、收支明细",
      "font_class": "dingdandingdanmingxishouzhimingxi",
      "unicode": "e78a",
      "unicode_decimal": 59274
    },
    {
      "icon_id": "6665545",
      "name": "商品惠",
      "font_class": "airudiantubiaohuizhi-zhuanqu_shangpinhui",
      "unicode": "e695",
      "unicode_decimal": 59029
    },
    {
      "icon_id": "9826647",
      "name": "数据统计",
      "font_class": "shujutongji2",
      "unicode": "e611",
      "unicode_decimal": 58897
    },
    {
      "icon_id": "19287391",
      "name": "数据统计",
      "font_class": "shujutongji3",
      "unicode": "e613",
      "unicode_decimal": 58899
    },
    {
      "icon_id": "20406446",
      "name": "订单_订单列表",
      "font_class": "dingdan_dingdanliebiao",
      "unicode": "e787",
      "unicode_decimal": 59271
    },
    {
      "icon_id": "21242868",
      "name": "订单",
      "font_class": "dingdan2",
      "unicode": "e63a",
      "unicode_decimal": 58938
    },
    {
      "icon_id": "24268735",
      "name": "正方体-面型",
      "font_class": "zhengfangti-mianxing",
      "unicode": "e705",
      "unicode_decimal": 59141
    },
    {
      "icon_id": "25885535",
      "name": "大数据、数据统计-08",
      "font_class": "a-dashujushujutongji-08",
      "unicode": "e896",
      "unicode_decimal": 59542
    },
    {
      "icon_id": "25885537",
      "name": "大数据、数据统计-09",
      "font_class": "a-dashujushujutongji-09",
      "unicode": "e899",
      "unicode_decimal": 59545
    },
    {
      "icon_id": "27830435",
      "name": "数据统计20备份 2",
      "font_class": "a-shujutongji20beifen2",
      "unicode": "e702",
      "unicode_decimal": 59138
    },
    {
      "icon_id": "1130",
      "name": "锁定",
      "font_class": "suoding",
      "unicode": "e603",
      "unicode_decimal": 58883
    },
    {
      "icon_id": "1334",
      "name": "解锁",
      "font_class": "jiesuo",
      "unicode": "e609",
      "unicode_decimal": 58889
    },
    {
      "icon_id": "7791969",
      "name": "用户名",
      "font_class": "ziyuanxhdpi",
      "unicode": "e648",
      "unicode_decimal": 58952
    },
    {
      "icon_id": "8455371",
      "name": "用户名",
      "font_class": "yonghuming2",
      "unicode": "e619",
      "unicode_decimal": 58905
    },
    {
      "icon_id": "18165266",
      "name": "锁,密码,锁定",
      "font_class": "lock",
      "unicode": "e881",
      "unicode_decimal": 59521
    },
    {
      "icon_id": "18165267",
      "name": "锁,密码,锁定",
      "font_class": "lock-full",
      "unicode": "e882",
      "unicode_decimal": 59522
    },
    {
      "icon_id": "18165278",
      "name": "锁,密码,开锁,解锁",
      "font_class": "unlock-full",
      "unicode": "e883",
      "unicode_decimal": 59523
    },
    {
      "icon_id": "18444822",
      "name": "用户名",
      "font_class": "yonghuming3",
      "unicode": "e612",
      "unicode_decimal": 58898
    },
    {
      "icon_id": "1070",
      "name": "礼物",
      "font_class": "liwu",
      "unicode": "e600",
      "unicode_decimal": 58880
    },
    {
      "icon_id": "145449",
      "name": "对话信息",
      "font_class": "duihuaxinxi",
      "unicode": "e639",
      "unicode_decimal": 58937
    },
    {
      "icon_id": "201228",
      "name": "3.1我的",
      "font_class": "31wode",
      "unicode": "e601",
      "unicode_decimal": 58881
    },
    {
      "icon_id": "278744",
      "name": "下箭头",
      "font_class": "xiajiantou",
      "unicode": "e6cc",
      "unicode_decimal": 59084
    },
    {
      "icon_id": "643733",
      "name": "充值",
      "font_class": "3",
      "unicode": "e602",
      "unicode_decimal": 58882
    },
    {
      "icon_id": "666888",
      "name": "手机",
      "font_class": "shouji",
      "unicode": "e692",
      "unicode_decimal": 59026
    },
    {
      "icon_id": "1221178",
      "name": "放大镜",
      "font_class": "fangdajing",
      "unicode": "e6e4",
      "unicode_decimal": 59108
    },
    {
      "icon_id": "1265486",
      "name": "手机",
      "font_class": "shouji1",
      "unicode": "e605",
      "unicode_decimal": 58885
    },
    {
      "icon_id": "1294881",
      "name": "对话",
      "font_class": "talk",
      "unicode": "e641",
      "unicode_decimal": 58945
    },
    {
      "icon_id": "2471349",
      "name": "对话框",
      "font_class": "duihuakuang",
      "unicode": "e66b",
      "unicode_decimal": 58987
    },
    {
      "icon_id": "2674878",
      "name": "箭头 上",
      "font_class": "jiantoushang",
      "unicode": "e62c",
      "unicode_decimal": 58924
    },
    {
      "icon_id": "2674928",
      "name": "箭头 右",
      "font_class": "jiantouyou",
      "unicode": "e62d",
      "unicode_decimal": 58925
    },
    {
      "icon_id": "2674929",
      "name": "箭头 下",
      "font_class": "jiantouxia",
      "unicode": "e62e",
      "unicode_decimal": 58926
    },
    {
      "icon_id": "4516199",
      "name": "电话卡",
      "font_class": "dianhuaqia",
      "unicode": "e733",
      "unicode_decimal": 59187
    },
    {
      "icon_id": "4633285",
      "name": "充值",
      "font_class": "chongzhi",
      "unicode": "e65c",
      "unicode_decimal": 58972
    },
    {
      "icon_id": "5387570",
      "name": "按钮-箭头向右",
      "font_class": "anniu-jiantouxiangyou",
      "unicode": "eb03",
      "unicode_decimal": 60163
    },
    {
      "icon_id": "5387913",
      "name": "按钮-箭头向右_o",
      "font_class": "anniu-jiantouxiangyou_o",
      "unicode": "eb8c",
      "unicode_decimal": 60300
    },
    {
      "icon_id": "7592559",
      "name": "24gl-headset",
      "font_class": "24gl-headset",
      "unicode": "ea0a",
      "unicode_decimal": 59914
    },
    {
      "icon_id": "7592572",
      "name": "24gf-headset",
      "font_class": "24gf-headset",
      "unicode": "ea0e",
      "unicode_decimal": 59918
    },
    {
      "icon_id": "8692387",
      "name": "礼物",
      "font_class": "liwu1",
      "unicode": "e63e",
      "unicode_decimal": 58942
    },
    {
      "icon_id": "15053945",
      "name": "放大镜",
      "font_class": "ic_search24px",
      "unicode": "e616",
      "unicode_decimal": 58902
    },
    {
      "icon_id": "18166107",
      "name": "礼物,礼物盒,礼品",
      "font_class": "gift",
      "unicode": "e8b5",
      "unicode_decimal": 59573
    },
    {
      "icon_id": "18169795",
      "name": "SIM卡,手机卡,电话卡",
      "font_class": "sim-full",
      "unicode": "e946",
      "unicode_decimal": 59718
    },
    {
      "icon_id": "6270980",
      "name": "三角形",
      "font_class": "sanjiaoxing",
      "unicode": "e6bd",
      "unicode_decimal": 59069
    },
    {
      "icon_id": "4354835",
      "name": "闭眼睛",
      "font_class": "biyanjing",
      "unicode": "e901",
      "unicode_decimal": 59649
    },
    {
      "icon_id": "6539450",
      "name": "眼睛",
      "font_class": "yanjing",
      "unicode": "e68c",
      "unicode_decimal": 59020
    },
    {
      "icon_id": "27724151",
      "name": "三角向下箭头",
      "font_class": "sanjiaoxiangxiajiantou",
      "unicode": "e688",
      "unicode_decimal": 59016
    },
    {
      "icon_id": "27724290",
      "name": "购物车",
      "font_class": "gouwuche",
      "unicode": "e697",
      "unicode_decimal": 59031
    },
    {
      "icon_id": "20654049",
      "name": "system",
      "font_class": "system",
      "unicode": "e604",
      "unicode_decimal": 58884
    },
    {
      "icon_id": "20656057",
      "name": "tft",
      "font_class": "tft",
      "unicode": "e606",
      "unicode_decimal": 58886
    },
    {
      "icon_id": "22928247",
      "name": "time",
      "font_class": "time",
      "unicode": "e618",
      "unicode_decimal": 58904
    }
  ]
}
